hyperspy/__init__.py
hyperspy/_lazy_signals.py
hyperspy/api.py
hyperspy/axes.py
hyperspy/component.py
hyperspy/components1d.py
hyperspy/components2d.py
hyperspy/conftest.py
hyperspy/decorators.py
hyperspy/defaults_parser.py
hyperspy/events.py
hyperspy/exceptions.py
hyperspy/extensions.py
hyperspy/hyperspy_extension.yaml
hyperspy/interactive.py
hyperspy/io.py
hyperspy/logger.py
hyperspy/model.py
hyperspy/roi.py
hyperspy/samfire.py
hyperspy/signal.py
hyperspy/signal_tools.py
hyperspy/signals.py
hyperspy/ui_registry.py
hyperspy/_components/__init__.py
hyperspy/_components/arctan.py
hyperspy/_components/bleasdale.py
hyperspy/_components/doniach.py
hyperspy/_components/error_function.py
hyperspy/_components/exponential.py
hyperspy/_components/expression.py
hyperspy/_components/gaussian.py
hyperspy/_components/gaussian2d.py
hyperspy/_components/gaussianhf.py
hyperspy/_components/heaviside.py
hyperspy/_components/logistic.py
hyperspy/_components/lorentzian.py
hyperspy/_components/offset.py
hyperspy/_components/polynomial.py
hyperspy/_components/power_law.py
hyperspy/_components/rc.py
hyperspy/_components/scalable_fixed_pattern.py
hyperspy/_components/skew_normal.py
hyperspy/_components/split_voigt.py
hyperspy/_components/voigt.py
hyperspy/_signals/__init__.py
hyperspy/_signals/common_signal1d.py
hyperspy/_signals/common_signal2d.py
hyperspy/_signals/complex_signal.py
hyperspy/_signals/complex_signal1d.py
hyperspy/_signals/complex_signal2d.py
hyperspy/_signals/lazy.py
hyperspy/_signals/signal1d.py
hyperspy/_signals/signal2d.py
hyperspy/data/__init__.py
hyperspy/data/artificial_data.py
hyperspy/data/two_gaussians.py
hyperspy/docstrings/__init__.py
hyperspy/docstrings/markers.py
hyperspy/docstrings/model.py
hyperspy/docstrings/parameters.py
hyperspy/docstrings/plot.py
hyperspy/docstrings/signal.py
hyperspy/docstrings/signal1d.py
hyperspy/docstrings/utils.py
hyperspy/drawing/__init__.py
hyperspy/drawing/figure.py
hyperspy/drawing/image.py
hyperspy/drawing/markers.py
hyperspy-2.2.0.dist-info/AUTHORS.txt
hyperspy-2.2.0.dist-info/COPYING.txt
hyperspy-2.2.0.dist-info/METADATA
hyperspy-2.2.0.dist-info/WHEEL
hyperspy-2.2.0.dist-info/top_level.txt
hyperspy-2.2.0.dist-info/RECORD
