Metadata-Version: 2.1
Name: hyperspy
Version: 2.2.0
Summary: Multidimensional data analysis toolbox
Author: The HyperSpy Community
License: GNU GENERAL PUBLIC LICENSE
Project-URL: Bug Reports, https://github.com/hyperspy/hyperspy/issues
Project-URL: Documentation, https://hyperspy.org/hyperspy-doc/current/index.html
Project-URL: Conda-forge, https://anaconda.org/conda-forge/hyperspy
Project-URL: Homepage, https://hyperspy.org
Project-URL: Support, https://gitter.im/hyperspy/hyperspy
Project-URL: Source, https://github.com/hyperspy/hyperspy
Keywords: cathodoluminescence,CL,EBSD,EDX,EDS,EELS,EFTEM,ICA,PCA,PES,STEM,TEM,curve fitting,data analysis,electron backscatter diffraction,electron energy loss spectroscopy,electron microscopy,energy dispersive x-ray spectroscopy,x-ray energy dispersive spectroscopy,hyperspectral,hyperspectrum,hyperspy,machine learning,microscopy,model,multidimensional,numpy,off-axis electron holography,photoluminescence,PL,python,quantification,scipy,spectroscopy,spectrum image
Classifier: Development Status :: 4 - Beta
Classifier: Framework :: Matplotlib
Classifier: Intended Audience :: Developers
Classifier: Intended Audience :: Science/Research
Classifier: License :: OSI Approved :: GNU General Public License v3 (GPLv3)
Classifier: Operating System :: OS Independent
Classifier: Programming Language :: Python :: 3.8
Classifier: Programming Language :: Python :: 3.9
Classifier: Programming Language :: Python :: 3.10
Classifier: Programming Language :: Python :: 3.11
Classifier: Programming Language :: Python :: 3.12
Classifier: Topic :: Scientific/Engineering
Classifier: Topic :: Scientific/Engineering :: Physics
Classifier: Topic :: Software Development :: Libraries
Requires-Python: >=3.8
License-File: COPYING.txt
License-File: AUTHORS.txt
Requires-Dist: cloudpickle
Requires-Dist: dask[array]>=2021.5.1
Requires-Dist: importlib-metadata>=3.6
Requires-Dist: jinja2
Requires-Dist: matplotlib>=3.6
Requires-Dist: natsort
Requires-Dist: numpy>=1.20.0
Requires-Dist: packaging
Requires-Dist: pint>=0.10
Requires-Dist: pooch
Requires-Dist: prettytable>=2.3
Requires-Dist: python-dateutil>=2.5.0
Requires-Dist: pyyaml
Requires-Dist: requests
Requires-Dist: rosettasciio[hdf5]
Requires-Dist: scikit-image>=0.18
Requires-Dist: scipy>=1.6.0
Requires-Dist: sympy>=1.6
Requires-Dist: tqdm>=4.9.0
Requires-Dist: traits>=4.5.0
Provides-Extra: all
Requires-Dist: hyperspy[gui-jupyter]; extra == "all"
Requires-Dist: hyperspy[gui-traitsui]; extra == "all"
Requires-Dist: hyperspy[ipython]; extra == "all"
Requires-Dist: hyperspy[learning]; extra == "all"
Requires-Dist: hyperspy[speed]; extra == "all"
Provides-Extra: coverage
Requires-Dist: pytest-cov; extra == "coverage"
Provides-Extra: dev
Requires-Dist: black; extra == "dev"
Requires-Dist: hyperspy[all]; extra == "dev"
Requires-Dist: hyperspy[coverage]; extra == "dev"
Requires-Dist: hyperspy[doc]; extra == "dev"
Requires-Dist: hyperspy[tests]; extra == "dev"
Provides-Extra: doc
Requires-Dist: holospy; extra == "doc"
Requires-Dist: IPython; extra == "doc"
Requires-Dist: pickleshare; extra == "doc"
Requires-Dist: numpydoc; extra == "doc"
Requires-Dist: pydata-sphinx-theme; extra == "doc"
Requires-Dist: setuptools-scm; extra == "doc"
Requires-Dist: sphinx-copybutton; extra == "doc"
Requires-Dist: sphinx-design; extra == "doc"
Requires-Dist: sphinx-favicon; extra == "doc"
Requires-Dist: sphinx-gallery; extra == "doc"
Requires-Dist: sphinx>=1.7; extra == "doc"
Requires-Dist: sphinxcontrib-mermaid; extra == "doc"
Requires-Dist: sphinxcontrib-towncrier>=0.3.0a0; extra == "doc"
Requires-Dist: towncrier<24; extra == "doc"
Provides-Extra: gui-jupyter
Requires-Dist: hyperspy-gui-ipywidgets>=2.0; extra == "gui-jupyter"
Requires-Dist: ipympl; extra == "gui-jupyter"
Provides-Extra: gui-traitsui
Requires-Dist: hyperspy-gui-traitsui>=2.0; extra == "gui-traitsui"
Provides-Extra: ipython
Requires-Dist: IPython!=8.0,>7.0; extra == "ipython"
Requires-Dist: ipyparallel; extra == "ipython"
Provides-Extra: learning
Requires-Dist: scikit-learn>=1.0.1; extra == "learning"
Provides-Extra: speed
Requires-Dist: numba; extra == "speed"
Requires-Dist: numexpr; extra == "speed"
Provides-Extra: tests
Requires-Dist: pytest-instafail; extra == "tests"
Requires-Dist: pytest-mpl; extra == "tests"
Requires-Dist: pytest-rerunfailures; extra == "tests"
Requires-Dist: pytest-xdist; extra == "tests"
Requires-Dist: pytest>=3.6; extra == "tests"
Requires-Dist: setuptools-scm; extra == "tests"
